{
  "UUID": "1E053173-EC02-426A-AB4D-B3E6B0340B78",
  "class": "com.runrev.engine.field",
  "customPropertySets": {
    "cREVGeneral": {
      "revUniqueID": "1364282980474"
    },
    "cREVTable": {
      "currentview": "image id 1008 of stack \"demo\""
    },
    "customKeys": {
      "innerShaddow": "",
      "kColorProps": "",
      "kMissingProps": ""
    }
  },
  "properties": {
    "altId": "0",
    "autoHilite": "true",
    "autoTab": "false",
    "backColor": "",
    "backPattern": "",
    "behavior": "",
    "blendLevel": "0",
    "borderColor": "",
    "borderPattern": "",
    "borderWidth": "2",
    "bottomColor": "",
    "bottomPattern": "",
    "cantSelect": "false",
    "colorOverlay": "",
    "disabled": "false",
    "dontSearch": "false",
    "dontWrap": "true",
    "dropShadow": "",
    "firstIndent": "0",
    "fixedLineHeight": "true",
    "focusColor": "",
    "focusPattern": "",
    "foreColor": "",
    "forePattern": "",
    "hGrid": "false",
    "hScroll": "0",
    "hScrollbar": "true",
    "hiliteColor": "",
    "hilitePattern": "",
    "hilitedLines": "",
    "htmlText": "<p></p>",
    "id": "1007",
    "ink": "srcCopy",
    "innerGlow": "",
    "innerShaddow": "",
    "layer": "3",
    "layerMode": "static",
    "listBehavior": "true",
    "lockLoc": "false",
    "lockText": "true",
    "margins": "8",
    "multipleHilites": "false",
    "name": "objects",
    "noncontiguousHilites": "false",
    "opaque": "true",
    "outerGlow": "",
    "padding": "0,0,580,286",
    "rect": "0,0,580,286",
    "scroll": "0",
    "scrollbarWidth": "16",
    "shadow": "false",
    "shadowColor": "",
    "shadowOffset": "4",
    "shadowPattern": "",
    "sharedText": "true",
    "showBorder": "true",
    "showFocusBorder": "true",
    "showLines": "false",
    "style": "scrolling",
    "tabStops": "",
    "textAlign": "left",
    "textFont": "",
    "textHeight": "",
    "textSize": "",
    "textStyle": "",
    "threeD": "true",
    "threeDHilite": "false",
    "toggleHilites": "false",
    "toolTip": "",
    "topColor": "",
    "topPattern": "",
    "traversalOn": "true",
    "vGrid": "false",
    "vScroll": "0",
    "vScrollbar": "true",
    "visible": "true"
  }
}