{
  "UUID": "64801fc4-de0c-4383-b9bd-78cb045910f5",
  "class": "com.runrev.engine.stack",
  "customPropertySets": {
    "customKeys": {
      "uSelectedChunk": ""
    }
  },
  "properties": {
    "altId": "0",
    "alwaysBuffer": "false",
    "backColor": "",
    "backPattern": "",
    "behavior": "",
    "blendLevel": "0",
    "borderColor": "",
    "borderPattern": "",
    "bottomColor": "",
    "bottomPattern": "",
    "cantAbort": "false",
    "cantDelete": "false",
    "cantModify": "false",
    "decorations": "title,menu,minimize,maximize,close",
    "destroyStack": "false",
    "destroyWindow": "false",
    "dynamicPaths": "false",
    "editMenus": "false",
    "externals": "",
    "focusColor": "",
    "focusPattern": "",
    "foreColor": "",
    "forePattern": "",
    "formatForPrinting": "false",
    "fullscreen": "false",
    "fullscreenmode": "",
    "hcAddressing": "false",
    "height": "400",
    "hiliteColor": "",
    "hilitePattern": "",
    "icon": "0",
    "iconic": "false",
    "linkColor": "",
    "linkHiliteColor": "",
    "linkVisitedColor": "",
    "liveResizing": "false",
    "maxHeight": "65535",
    "maxWidth": "65535",
    "menubar": "",
    "metal": "false",
    "minHeight": "32",
    "minWidth": "32",
    "name": "Data Grid Templates 1376537700946",
    "resizable": "true",
    "scalefactor": "1",
    "shadow": "true",
    "shadowColor": "",
    "shadowOffset": "4",
    "shadowPattern": "",
    "showInvisibles": "",
    "stackFiles": "",
    "startUpIconic": "false",
    "style": "toplevel",
    "systemWindow": "false",
    "textFont": "",
    "textSize": "",
    "textStyle": "",
    "title": "",
    "topColor": "",
    "topPattern": "",
    "underlineLinks": "",
    "visible": "true",
    "width": "600",
    "windowManagerPlace": "false",
    "windowShape": "0"
  }
}